Metadata-Version: 1.1
Name: col2col
Version: 0.2.2
Summary: Python package to convert units by column in XLSX files
Home-page: https://github.com/gabriel23cg/col2col
Author: Diego Rodriguez, Gabriel Capeans
Author-email: diego.cacheiras@gmail.com, gabriel23cg@gmail.com
License: MIT License
